tgedr/pycode/__init__.py
tgedr/pycode/pyspark/data_exploration.py
tgedr/pycode/utils/reflection.py
tgedr_pycode-0.0.24.dist-info/METADATA
tgedr_pycode-0.0.24.dist-info/WHEEL
tgedr_pycode-0.0.24.dist-info/top_level.txt
tgedr_pycode-0.0.24.dist-info/RECORD
